<?xml version="1.0" encoding="utf-8"?>
<law nr="4" parliament="149c" year="1978">
  <name>Lög um aðild Íslands að alþjóðasamningi um ræðissamband</name>
  <num-and-date>
    <date>1978-02-24</date>
    <num>4</num>
  </num-and-date>
  <minister-clause>&lt;a href=&quot;http://www.althingi.is//dba-bin/ferill.pl?ltg=99&amp;amp;mnr=35&quot;&gt; &lt;i&gt; Ferill málsins á Alþingi. &lt;/i&gt; &lt;/a&gt; &lt;a href=&quot;http://www.althingi.is/altext/99/s/pdf/0036.pdf&quot;&gt; &lt;i&gt; Frumvarp til laga. &lt;/i&gt; &lt;/a&gt; &lt;br/&gt; &lt;br/&gt; &lt;small&gt; &lt;b&gt; Tóku gildi 6. apríl 1978. &lt;/b&gt; &lt;/small&gt; &lt;br/&gt; Ef í lögum þessum er getið um ráðherra eða ráðuneyti án þess að málefnasvið sé tilgreint sérstaklega eða til þess vísað, er átt við &lt;b&gt; utanríkisráðherra &lt;/b&gt; eða &lt;b&gt; utanríkisráðuneyti &lt;/b&gt; sem fer með lög þessi. Upplýsingar um málefnasvið ráðuneyta skv. forsetaúrskurði er að finna &lt;a href=&quot;2018119.html&quot;&gt; hér. &lt;/a&gt;</minister-clause>
  <art nr="1">
    <nr-title>1. gr.</nr-title>
    <subart nr="1">
      <sen>Ríkisstjórninni er heimilt að gerast aðili fyrir Íslands hönd að alþjóðasamningi um ræðissamband sem gerður var í Vínarborg 24. apríl 1963 og prentaður er sem fylgiskjal með lögum þessum, svo og að viðbótarbókunum varðandi ríkisborgararétt og skyldubundna lausn deilumála.</sen>
    </subart>
    <subart nr="2">
      <sen>Ákvæði samningsins skulu hafa lagagildi á Íslandi.</sen>
    </subart>
  </art>
  <art nr="2">
    <nr-title>2. gr.</nr-title>
    <subart nr="1">
      <sen>Ráðherra getur sett nánari reglur um framkvæmd laga þessara.</sen>
    </subart>
  </art>
  <art nr="3">
    <nr-title>3. gr.</nr-title>
    <subart nr="1">
      <sen>Lög þessi öðlast þegar gildi.</sen>
      <sen>
        <a href="http://www.althingi.is/vefur/lagas-hlp.html" title="Hér hefur annaðhvort verið fellt brott ákvæði um breytingar á öðrum lögum eða um brottfall þeirra, eða úrelt ákvæði til bráðabirgða. Sjá 7. lið í leiðbeiningum um notkun lagasafns.">…</a>
      </sen>
    </subart>
  </art>
</law>
