<?xml version="1.0" encoding="utf-8"?>
<law nr="45" year="1989">
  <name>Lög um stofnun hlutafélags um ríkisprentsmiðjuna Gutenberg</name>
  <num-and-date>
    <date>1989-05-23</date>
    <num>45</num>
    <original>1989 nr. 45 23. maí</original>
  </num-and-date>
  <footnotes>
    <footnote nr="1">
      <footnote-sen>Sjá Lagasafn 1990, d. 1949.</footnote-sen>
      <location type="pointer">
        <name before-mark="^Lög um stofnun hlutafélags um ríkisprentsmiðjuna Gutenberg " after-mark="$">1</name>
      </location>
    </footnote>
  </footnotes>
  <minister-clause>&lt;a href=&quot;http://www.althingi.is//dba-bin/ferill.pl?ltg=111&amp;amp;mnr=410&quot;&gt; &lt;i&gt; Ferill málsins á Alþingi. &lt;/i&gt; &lt;/a&gt; &lt;a href=&quot;http://www.althingi.is/altext/111/s/0770.html&quot;&gt; &lt;i&gt; Frumvarp til laga. &lt;/i&gt; &lt;/a&gt; &lt;br/&gt; &lt;br/&gt; &lt;small&gt; &lt;b&gt; Tóku gildi 30. maí 1989. &lt;/b&gt; &lt;/small&gt;</minister-clause>
</law>
