<?xml version="1.0" encoding="utf-8"?>
<law nr="87" parliament="150b" year="2003">
  <name>Lög um Orkustofnun</name>
  <num-and-date>
    <date>2003-03-26</date>
    <num>87</num>
    <original>2003 nr. 87 26. mars</original>
  </num-and-date>
  <minister-clause>&lt;a href=&quot;http://www.althingi.is//dba-bin/ferill.pl?ltg=128&amp;amp;mnr=544&quot;&gt; &lt;i&gt; Ferill málsins á Alþingi. &lt;/i&gt; &lt;/a&gt; &lt;a href=&quot;http://www.althingi.is/altext/128/s/0891.html&quot;&gt; &lt;i&gt; Frumvarp til laga. &lt;/i&gt; &lt;/a&gt; &lt;br/&gt; &lt;br/&gt; &lt;small&gt; &lt;b&gt; Tóku gildi 10. apríl 2003 en komu til framkvæmda 1. júlí sama ár. &lt;/b&gt; &lt;em&gt; Breytt með: &lt;/em&gt; &lt;a href=&quot;/altext/stjt/2007.048.html&quot;&gt; L. 48/2007 &lt;/a&gt; (tóku gildi 3. apríl 2007). &lt;a href=&quot;/altext/stjt/2007.167.html&quot;&gt; L. 167/2007 &lt;/a&gt; (tóku gildi 1. jan. 2008). &lt;a href=&quot;/altext/stjt/2008.070.html&quot;&gt; L. 70/2008 &lt;/a&gt; (tóku gildi 1. jan. 2009). &lt;a href=&quot;/altext/stjt/2011.126.html&quot;&gt; L. 126/2011 &lt;/a&gt; (tóku gildi 30. sept. 2011). &lt;a href=&quot;/altext/stjt/2014.110.html&quot;&gt; L. 110/2014 &lt;/a&gt; (tóku gildi 1. jan. 2015). &lt;a href=&quot;/altext/stjt/2019.112.html&quot;&gt; L. 112/2019 &lt;/a&gt; (tóku gildi 19. sept. 2019 nema a- og b-liður 6. gr. sem taka gildi 1. jan. 2020). &lt;br/&gt; &lt;/small&gt; &lt;br/&gt; Ef í lögum þessum er getið um ráðherra eða ráðuneyti án þess að málefnasvið sé tilgreint sérstaklega eða til þess vísað, er átt við &lt;b&gt; ferðamála-, iðnaðar- og nýsköpunarráðherra &lt;/b&gt; eða &lt;b&gt; atvinnuvega- og nýsköpunarráðuneyti &lt;/b&gt; sem fer með lög þessi. Upplýsingar um málefnasvið ráðuneyta skv. forsetaúrskurði er að finna &lt;a href=&quot;2018119.html&quot;&gt; hér. &lt;/a&gt;</minister-clause>
  <art nr="1">
    <nr-title>1. gr.</nr-title>
    <subart nr="1">
      <sen>Orkustofnun er sérstök ríkisstofnun sem heyrir undir yfirstjórn ráðherra.</sen>
      <sen>Orkustofnun er sjálfstæð í ákvörðunum sínum þegar stofnunin sinnir raforkueftirliti samkvæmt raforkulögum.</sen>
    </subart>
    <footnotes>
      <footnote href="https://www.althingi.is/altext/stjt/2011.126.html" law-art="375" law-nr="126" law-year="2011" nr="1">
        <footnote-sen>L. 126/2011, 375. gr.</footnote-sen>
        <location type="range">
          <art>1</art>
          <subart>1</subart>
          <sen words="ráðherra">1</sen>
        </location>
      </footnote>
      <footnote href="https://www.althingi.is/altext/stjt/2019.112.html" law-art="8" law-nr="112" law-year="2019" nr="2">
        <footnote-sen>L. 112/2019, 8. gr.</footnote-sen>
        <location type="range">
          <art>1</art>
          <subart>1</subart>
          <sen words="Orkustofnun er sjálfstæð í ákvörðunum sínum þegar stofnunin sinnir raforkueftirliti samkvæmt raforkulögum.">2</sen>
        </location>
      </footnote>
    </footnotes>
  </art>
  <art nr="2">
    <nr-title>2. gr.</nr-title>
    <subart nr="1">
      <sen>Hlutverk Orkustofnunar er:</sen>
      <numart nr="1" type="numeric">
        <nr-title>1.</nr-title>
        <sen>að vera ríkisstjórninni til ráðuneytis um orkumál og önnur auðlindamál sem stofnuninni eru falin með lögum og veita stjórnvöldum ráðgjöf og umsagnir um þau mál,</sen>
      </numart>
      <numart nr="2" type="numeric">
        <nr-title>2.</nr-title>
        <sen>að standa fyrir rannsóknum á orkubúskap þjóðarinnar, á orkulindum landsins og hafsbotnsins og á öðrum jarðrænum auðlindum þannig að unnt sé að meta þær og veita stjórnvöldum ráðgjöf um skynsamlega og hagkvæma nýtingu þeirra,</sen>
      </numart>
      <numart nr="3" type="numeric">
        <nr-title>3.</nr-title>
        <sen>að safna gögnum um orkulindir og aðrar jarðrænar auðlindir, nýtingu þeirra og orkubúskap landsmanna, varðveita þau og miðla upplýsingum til stjórnvalda og almennings,</sen>
      </numart>
      <numart nr="4" type="numeric">
        <nr-title>4.</nr-title>
        <sen>að vinna að áætlanagerð til langs tíma um orkubúskap þjóðarinnar og hagnýtingu orkulinda og annarra jarðrænna auðlinda landsins og hafsbotnsins,</sen>
      </numart>
      <numart nr="5" type="numeric">
        <nr-title>5.</nr-title>
        <sen>að stuðla að samvinnu þeirra sem sinna orkurannsóknum og samræmingu á rannsóknarverkefnum,</sen>
      </numart>
      <numart nr="6" type="numeric">
        <nr-title>6.</nr-title>
        <sen>að fylgjast í umboði ráðherra með framkvæmd opinberra leyfa sem gefin eru út til rannsóknar og nýtingar jarðrænna auðlinda og reksturs orkuvera og annarra meiri háttar orkumannvirkja,</sen>
      </numart>
      <numart nr="7" type="numeric">
        <nr-title>7.</nr-title>
        <sen>að annast umsýslu Orkusjóðs.</sen>
      </numart>
    </subart>
    <subart nr="2">
      <sen>Orkustofnun skal enn fremur annast önnur stjórnsýsluverkefni sem stofnuninni eru falin samkvæmt lögum, stjórnvaldsfyrirmælum eða ákvörðun ráðherra.</sen>
    </subart>
    <subart nr="3">
      <sen>Orkustofnun er heimilt að gera samninga við fyrirtæki eða stofnanir um framkvæmd skilgreindra verkefna, sbr. 2. og 3. tölul. 1. mgr.</sen>
      <sen>Leita skal staðfestingar ráðherra á samningum sem gerðir eru til lengri tíma en tveggja ára.</sen>
    </subart>
    <subart nr="4">
      <sen>Orkustofnun er heimilt að hafa samvinnu við stofnanir eða fyrirtæki um þjónustustarfsemi, svo sem rekstur húsnæðis, símvörslu, tölvuþjónustu o.fl.</sen>
    </subart>
    <subart nr="5">
      <sen>Til að sinna hlutverki sínu skv. 3. tölul. 1. mgr. er Orkustofnun heimilt að krefjast gagna sem varða nýtingu á jarðrænum auðlindum, orkuframleiðslu og orkunotkun, þ.m.t. gagna um innflutning, geymslu og sölu á jarðefnaeldsneyti.</sen>
      <sen>Skylt er þeim sem stunda atvinnurekstur er varðar framangreint að afhenda stofnuninni nauðsynleg gögn innan frests sem hún tilgreinir.</sen>
      <sen>Í reglugerð skal kveða nánar á um tegund gagna, gæði þeirra og skilafrest.</sen>
    </subart>
    <subart nr="6">
      <sen>Sé gögnum ekki skilað innan tilgreinds frests er Orkustofnun heimilt að leggja dagsektir á viðkomandi fyrirtæki eða stofnun.</sen>
      <sen>Dagsektir geta numið 10–100 þús. kr. á dag.</sen>
      <sen>Ákvörðun um dagsektir skal tilkynnt bréflega á sannanlegan hátt þeim sem hún beinist að.</sen>
      <sen>Ákvarðanir um að leggja á dagsektir eru aðfararhæfar.</sen>
      <sen>Innheimtar dagsektir skulu renna í ríkissjóð að frádregnum kostnaði við innheimtuna.</sen>
    </subart>
    <footnotes>
      <footnote nr="1">
        <footnote-sen>&lt;a href=&quot;https://www.reglugerd.is/reglugerdir/allar/nr/870-2013&quot;&gt;Rg. 870/2013&lt;/a&gt;. &lt;a href=&quot;https://www.reglugerd.is/reglugerdir/allar/nr/549-2015&quot;&gt;Rg. 549/2015&lt;/a&gt;.</footnote-sen>
        <location type="pointer">
          <art>2</art>
          <subart>5</subart>
          <sen after-mark=" skal kveða nánar á um tegund gagna, gæði þeirra og skilafrest.$" before-mark="^Í reglugerð ">3</sen>
        </location>
      </footnote>
      <footnote href="https://www.althingi.is/altext/stjt/2007.048.html" law-art="1" law-nr="48" law-year="2007" nr="2">
        <footnote-sen>L. 48/2007, 1. gr.</footnote-sen>
        <location type="range">
          <start>
            <art>2</art>
            <subart>5</subart>
            <sen>1</sen>
          </start>
          <end>
            <art>2</art>
            <subart>6</subart>
            <sen>5</sen>
          </end>
        </location>
      </footnote>
    </footnotes>
  </art>
  <art nr="3">
    <nr-title>3. gr.</nr-title>
    <footnotes>
      <footnote href="https://www.althingi.is/altext/stjt/2008.070.html#G7" law-art="7" law-nr="70" law-year="2008" nr="1">
        <footnote-sen>L. 70/2008, 7. gr.</footnote-sen>
        <location type="deletion">
          <art>3</art>
          <nr-title after-mark="$" before-mark="^3. gr. ">1</nr-title>
        </location>
      </footnote>
    </footnotes>
  </art>
  <art nr="4">
    <nr-title>4. gr.</nr-title>
    <subart nr="1">
      <sen>Orkustofnun skal gera framkvæmdaáætlun til fjögurra ára í senn um þau verkefni sem stofnunin vinnur að skv. 2. og 3. tölul. 1. mgr. 2. gr.</sen>
      <sen>Skal hún endurskoðuð árlega og lögð fyrir ráðherra til staðfestingar.</sen>
    </subart>
  </art>
  <art nr="5">
    <nr-title>5. gr.</nr-title>
    <subart nr="1">
      <sen>Ráðherra skipar forstöðumann Orkustofnunar til fimm ára í senn.</sen>
      <sen>Nefnist hann orkumálastjóri.</sen>
      <sen>Orkumálastjóri fer með stjórn og daglegan rekstur Orkustofnunar.</sen>
      <sen>Orkumálastjóri ræður annað starfslið stofnunarinnar.</sen>
    </subart>
  </art>
  <art nr="6">
    <nr-title>6. gr.</nr-title>
    <footnotes>
      <footnote href="https://www.althingi.is/altext/stjt/2014.110.html" law-art="1" law-nr="110" law-year="2014" nr="1">
        <footnote-sen>L. 110/2014, 1. gr.</footnote-sen>
        <location type="deletion">
          <art>6</art>
          <nr-title after-mark="$" before-mark="^6. gr. ">1</nr-title>
        </location>
      </footnote>
    </footnotes>
  </art>
  <art nr="7">
    <nr-title>7. gr.</nr-title>
    <subart nr="1">
      <sen>Ef ráðist er í orkuframkvæmdir sem undirbúnar hafa verið með rannsóknum og áætlunargerð sem kostaðar hafa verið með fé ríkisins skal framkvæmdaraðili endurgreiða Orkustofnun þann kostnað þegar honum er veitt virkjunar- eða nýtingarleyfi.</sen>
      <sen>Kostnaðarliðir skulu framreiknaðir með vísitölu neysluverðs til gjalddaga.</sen>
      <sen>Orkustofnun skal leggja fram rökstudda greinargerð um endurgreiðslukröfu í hverju tilviki.</sen>
      <sen>Rísi ágreiningur um greiðsluna skal hann lagður í gerð þriggja manna að kröfu annars aðila eða beggja á grundvelli laga nr. 53/1989, um samningsbundna gerðardóma.</sen>
      <sen>Endurgreiðslu skal að fullu lokið eigi síðar en sjö árum eftir að leyfi hefur verið gefið út.</sen>
      <sen>Endurgreiddu fé skal varið til að fjármagna rannsóknir á orkulindum landsins sem gerðar eru skv. 2. tölul. 1. mgr. 2. gr. laga þessara.</sen>
    </subart>
  </art>
  <art nr="8">
    <nr-title>8. gr.</nr-title>
    <subart nr="1">
      <sen>Orkusjóður er eign ríkisins og ber það ábyrgð á skuldbindingum hans.</sen>
      <sen>Yfirumsjón með sjóðnum er í höndum ráðherra.</sen>
      <sen>Orkustofnun annast daglega umsýslu Orkusjóðs.</sen>
    </subart>
    <subart nr="2">
      <sen>Hlutverk Orkusjóðs er að stuðla að hagkvæmri nýtingu orkulinda landsins með styrkjum eða lánum, einkum til aðgerða er miða að því að draga úr notkun jarðefnaeldsneytis.</sen>
      <sen>Þetta skal gert með því:</sen>
      <numart nr="1" type="numeric">
        <nr-title>1.</nr-title>
        <sen>að veita lán til að leita að jarðvarma þar sem hagkvæmt þykir til að draga úr kostnaði þjóðfélagsins við upphitun húsnæðis,</sen>
      </numart>
      <numart nr="2" type="numeric">
        <nr-title>2.</nr-title>
        <sen>,</sen>
      </numart>
      <numart nr="3" type="numeric">
        <nr-title>3.</nr-title>
        <sen>að veita styrki til sérstakra verkefna á sviði hagkvæmrar orkunotkunar, þ.m.t. til fræðslu og upplýsingastarfsemi,</sen>
      </numart>
      <numart nr="4" type="numeric">
        <nr-title>4.</nr-title>
        <sen>að veita styrki til verkefna sem stuðla að nýtingu á innlendri orku í stað jarðefnaeldsneytis og styrkja alþjóðasamvinnu um slík verkefni.</sen>
      </numart>
    </subart>
    <subart nr="3">
      <sen>Orkusjóði er ekki heimilt að veita Orkustofnun styrki eða lán af fé sjóðsins.</sen>
    </subart>
    <subart nr="4">
      <sen>Tekjur Orkusjóðs eru:</sen>
      <numart nr="1" type="numeric">
        <nr-title>1.</nr-title>
        <sen>vextir af fé sjóðsins,</sen>
      </numart>
      <numart nr="2" type="numeric">
        <nr-title>2.</nr-title>
        <sen>fé það sem veitt er í fjárlögum hverju sinni.</sen>
      </numart>
    </subart>
    <subart nr="5">
      <sen>Heimilt er að semja við aðila, sem hafa leyfi til fjárvörslu lögum samkvæmt, um umsjón og trygga vörslu á fé sjóðsins.</sen>
    </subart>
    <subart nr="6">
      <sen>Ráðherra skipar þrjá menn í ráðgjafarnefnd Orkusjóðs til fjögurra ára, þar af skal einn skipaður formaður.</sen>
      <sen>Ráðgjafarnefndin skal gera tillögur til ráðherra um lánveitingar og einstakar greiðslur úr Orkusjóði samkvæmt fjárhags- og greiðsluáætlun sjóðsins.</sen>
    </subart>
    <subart nr="7">
      <sen>Í reglugerð skal mæla nánar fyrir um skilyrði fyrir framlögum úr Orkusjóði, undirbúning úthlutunar, lánveitingar, þ.m.t. um vexti og önnur útlánakjör, greiðslur, eftirlit með framkvæmdum sem Orkusjóður veitir fé til og heimildir til að fella niður endurgreiðsluskyldu lántaka.</sen>
    </subart>
    <footnotes>
      <footnote href="https://www.althingi.is/altext/stjt/2011.126.html" law-art="375" law-nr="126" law-year="2011" nr="1">
        <footnote-sen>L. 126/2011, 375. gr.</footnote-sen>
        <location type="range">
          <art>8</art>
          <subart>1</subart>
          <sen words="ráðherra">2</sen>
        </location>
      </footnote>
      <footnote href="https://www.althingi.is/altext/stjt/2014.110.html" law-art="2" law-nr="110" law-year="2014" nr="2">
        <footnote-sen>L. 110/2014, 2. gr.</footnote-sen>
        <location type="deletion">
          <art>8</art>
          <subart>2</subart>
          <numart>2</numart>
          <sen after-mark="$" before-mark="^">1</sen>
        </location>
        <location type="range">
          <start>
            <art>8</art>
            <subart>6</subart>
            <sen>1</sen>
          </start>
          <end>
            <art>8</art>
            <subart>6</subart>
            <sen>2</sen>
          </end>
        </location>
      </footnote>
      <footnote nr="3">
        <footnote-sen>&lt;a href=&quot;https://www.reglugerd.is/reglugerdir/allar/nr/185-2016&quot;&gt;Rg. 185/2016&lt;/a&gt;.</footnote-sen>
        <location type="pointer">
          <art>8</art>
          <subart>7</subart>
          <sen after-mark=" skal mæla nánar fyrir um skilyrði fyrir framlögum úr Orkusjóði, undirbúning úthlutunar, lánveitingar, þ.m.t. um vexti og önnur útlánakjör, greiðslur, eftirlit með framkvæmdum sem Orkusjóður veitir fé til og heimildir til að fella niður endurgreiðsluskyldu lántaka.$" before-mark="^Í reglugerð ">1</sen>
        </location>
      </footnote>
    </footnotes>
  </art>
  <art nr="9">
    <nr-title>9. gr.</nr-title>
    <subart nr="1">
      <sen>Ráðherra getur í reglugerð mælt nánar fyrir um starfsemi Orkustofnunar og framkvæmd laga þessara.</sen>
    </subart>
    <footnotes>
      <footnote nr="1">
        <footnote-sen>&lt;a href=&quot;https://www.reglugerd.is/reglugerdir/allar/nr/400-2009&quot;&gt;Rg. 400/2009&lt;/a&gt;.</footnote-sen>
        <location type="pointer">
          <art>9</art>
          <subart>1</subart>
          <sen after-mark=" mælt nánar fyrir um starfsemi Orkustofnunar og framkvæmd laga þessara.$" before-mark="^Ráðherra getur í reglugerð ">1</sen>
        </location>
      </footnote>
    </footnotes>
  </art>
  <art nr="10">
    <nr-title>10. gr.</nr-title>
    <subart nr="1">
      <sen>Lög þessi öðlast þegar gildi en koma til framkvæmda 1. júlí 2003.</sen>
    </subart>
    <subart nr="2">
      <sen>
        <a href="http://www.althingi.is/altext/stjt/2003.087.html" title="Hér hefur annaðhvort verið fellt brott ákvæði um breytingar á öðrum lögum eða um brottfall þeirra, eða úrelt ákvæði til bráðabirgða.">…</a>
      </sen>
    </subart>
  </art>
  <chapter nr="t" nr-type="name" type="temporary-clauses">
    <name>Ákvæði til bráðabirgða.</name>
    <art nr="I" number-type="roman" roman-nr="1">
      <nr-title>I.</nr-title>
      <subart nr="1">
        <sen>Iðnaðarráðherra ákveður í samráði við Orkustofnun og Íslenskar orkurannsóknir hvaða eignir og skuldir Orkustofnunar skuli tilheyra hvorri stofnun.</sen>
        <sen>Þó skulu allar rannsóknaniðurstöður og gagnasöfn sem fjármögnuð hafa verið með opinberu fé áfram vera eign Orkustofnunar.</sen>
      </subart>
    </art>
    <art nr="II" number-type="roman" roman-nr="2">
      <nr-title>II.</nr-title>
      <subart nr="1">
        <sen>Starfsemi vatnamælinga Orkustofnunar lýtur yfirstjórn umhverfisráðherra frá 1. janúar 2008.</sen>
        <sen>Umhverfisráðherra skal vinna að sameiningu Veðurstofu Íslands og vatnamælinga Orkustofnunar í eina stofnun eigi síðar en 1. janúar 2009.</sen>
        <sen>Orkustofnun annast starfsemi vatnamælinga, undir yfirstjórn umhverfisráðherra, þar til ný stofnun tekur til starfa.</sen>
      </subart>
      <footnotes>
        <footnote href="https://www.althingi.is/altext/stjt/2007.167.html" law-art="33" law-nr="167" law-year="2007" nr="1">
          <footnote-sen>L. 167/2007, 33. gr.</footnote-sen>
          <location type="range">
            <start>
              <chapter>t</chapter>
              <art>II</art>
              <nr-title>1</nr-title>
            </start>
            <end>
              <chapter>t</chapter>
              <art>II</art>
              <subart>1</subart>
              <sen>3</sen>
            </end>
          </location>
        </footnote>
      </footnotes>
    </art>
  </chapter>
</law>
