<?xml version='1.0' encoding='utf-8'?>
<advert type="law" record-id="4947cbf2-9025-468f-be68-7ec983dae7a3" year="2024" nr="49" published-date="2024-05-29" applied-to-codex-version="154b">
  <affected-laws>
    <affected-law nr="38" year="2018">38/2018</affected-law>
  </affected-laws>
  <description>um breytingu á lögum um þjónustu við fatlað fólk með langvarandi stuðningsþarfir, nr. 38/2018 (reglugerðarheimild).</description>
  <advert-art nr="1" processed="false" affected-law-nr="38" affected-law-year="2018">
    <original>
      <p style="text-align: justify;">Við 8. gr. laganna bætist ný málsgrein, svohljóðandi:</p>
      <p style="text-align: justify;">Ráðherra er heimilt að kveða nánar á um stoðþjónustu í reglugerð, svo sem um aðstoðar­manna­kort fatlaðs fólks og fæðisfé starfsfólks sem matast með notanda.</p>
    </original>
  </advert-art>
  <advert-art nr="2" processed="false" affected-law-nr="38" affected-law-year="2018">
    <original>
      <p style="text-align: justify;">Á eftir 1. mgr. 40. gr. laganna kemur ný málsgrein, svohljóðandi:</p>
      <p style="text-align: justify;">Ráðherra er heimilt að setja reglugerðir um nánari framkvæmd laga þessara, þar á meðal um:</p>
      <ol>
        <li style="text-align: justify;">stoðþjónustu, sbr. 8. gr.,</li>
        <li style="text-align: justify;">stuðningsfjölskyldur, sbr. 15. gr.,</li>
        <li style="text-align: justify;">frístundaþjónustu, sbr. 16. gr.,</li>
        <li style="text-align: justify;">framkvæmd styrkveitinga, sbr. 25. gr.</li>
      </ol>
    </original>
  </advert-art>
  <advert-art nr="3" processed="false" affected-law-nr="38" affected-law-year="2018">
    <original>
      <p style="text-align: justify;">Lög þessi öðlast þegar gildi.</p>
    </original>
  </advert-art>
  <signed-when>Gjört á Bessastöðum, 21. maí 2024.</signed-when>
</advert>
